nokiaapp/__init__.py
nokiaapp/decorators.py
nokiaapp/defaults.py
nokiaapp/legacy_urls.py
nokiaapp/models.py
nokiaapp/urls.py
nokiaapp/utils.py
nokiaapp/views.py
nokiaapp/migrations/0001_initial.py
nokiaapp/migrations/0002_help_text.py
nokiaapp/migrations/0003_rename_nokiaapp.py
nokiaapp/migrations/0004_add_oauth2_fields.py
nokiaapp/migrations/0005_migrate_oauth_tokens.py
nokiaapp/migrations/0006_remove_nokiauser_access_token_secret.py
nokiaapp/migrations/__init__.py
nokiaapp/templates/nokia/error.html
nokiaapp/templatetags/__init__.py
nokiaapp/templatetags/nokia.py
nokiaapp/tests/__init__.py
nokiaapp/tests/base.py
nokiaapp/tests/test_integration.py
nokiaapp/tests/test_models.py
nokiaapp/tests/test_retrieval.py
nokiaapp/tests/test_utils.py
django_nokia-0.0.7.dist-info/AUTHORS
django_nokia-0.0.7.dist-info/LICENSE.txt
django_nokia-0.0.7.dist-info/METADATA
django_nokia-0.0.7.dist-info/WHEEL
django_nokia-0.0.7.dist-info/top_level.txt
django_nokia-0.0.7.dist-info/RECORD
