Metadata-Version: 2.1
Name: django-nokia
Version: 0.0.7
Summary: Django integration for python-nokia
Home-page: https://github.com/orcasgit/django-nokia/
Author: orcas
Author-email: bpitcher@orcasinc.com
License: License :: OSI Approved :: Apache Software License
Platform: UNKNOWN
Classifier: Development Status :: 3 - Alpha
Classifier: License :: OSI Approved :: Apache Software License
Classifier: Environment :: Web Environment
Classifier: Framework :: Django
Classifier: Intended Audience :: Developers
Classifier: Programming Language :: Python
Classifier: Programming Language :: Python :: 2
Classifier: Programming Language :: Python :: 2.7
Classifier: Programming Language :: Python :: 3
Classifier: Programming Language :: Python :: 3.4
Classifier: Programming Language :: Python :: 3.5
Classifier: Programming Language :: Python :: 3.6
Classifier: Programming Language :: Python :: Implementation
Classifier: Programming Language :: Python :: Implementation :: PyPy
Requires-Dist: setuptools
Requires-Dist: nokia (<1.2,>=1.1)
Requires-Dist: arrow (<0.5.0,>=0.4.0)
Requires-Dist: python-dateutil (<2.5.0,>=2.3.0)
Requires-Dist: requests-oauthlib (>=0.4.2)
